{"2022-01-19": {"date": "2022-01-19", "iron": 0, "steel": 0, "mithril": 0, "adamant": 0, "rune": 0, "dragon": 0}, "2022-01-26": {"date": "2022-01-26", "iron": 425, "steel": 1070, "mithril": 2105, "adamant": 4060, "rune": 8395, "dragon": 12635}, "2022-01-27": {"date": "2022-01-27", "iron": 430, "steel": 1095, "mithril": 2175, "adamant": 4235, "rune": 8685, "dragon": 13500}, "2022-01-28": {"date": "2022-01-28", "iron": 435, "steel": null, "mithril": 2320, "adamant": 4595, "rune": 9275, "dragon": 15210}, "2022-01-29": {"date": "2022-01-29", "iron": null, "steel": 1200, "mithril": 2525, "adamant": 5110, "rune": 10150, "dragon": 16235}, "2022-01-30": {"date": "2022-01-30", "iron": 455, "steel": 1260, "mithril": 2785, "adamant": 5690, "rune": 11115, "dragon": 17375}, "2022-01-31": {"date": "2022-01-31", "iron": null, "steel": 1310, "mithril": 3090, "adamant": 6375, "rune": 12210, "dragon": 18590}, "2022-02-01": {"date": "2022-02-01", "iron": 465, "steel": 1360, "mithril": 3250, "adamant": 7200, "rune": 13510, "dragon": 19800}, "2022-02-02": {"date": "2022-02-02", "iron": 465, "steel": 1400, "mithril": 3390, "adamant": 7705, "rune": 15120, "dragon": 21145}, "2022-02-03": {"date": "2022-02-03", "iron": 470, "steel": 1445, "mithril": 3515, "adamant": 7955, "rune": 15730, "dragon": 22340}}